flask_pyjwt/__init__.py
flask_pyjwt/exceptions.py
flask_pyjwt/jwt.py
flask_pyjwt/manager.py
flask_pyjwt/py.typed
flask_pyjwt/typing.py
flask_pyjwt/utils.py
flask_pyjwt-0.3.0.dist-info/LICENSE
flask_pyjwt-0.3.0.dist-info/METADATA
flask_pyjwt-0.3.0.dist-info/WHEEL
flask_pyjwt-0.3.0.dist-info/RECORD
