Metadata-Version: 2.1
Name: flask-pyjwt
Version: 0.3.0
Summary: Flask extension for creating, verifying, and requiring the presence of JWTs
Home-page: https://flask-pyjwt.readthedocs.io/
License: MIT
Keywords: flask,authentication,jwt,security
Author: Carson Mullins
Author-email: septem151@protonmail.com
Requires-Python: >=3.8,<4.0
Classifier: Development Status :: 4 - Beta
Classifier: Framework :: Flask
Classifier: Intended Audience :: Developers
Classifier: License :: OSI Approved :: MIT License
Classifier: Programming Language :: Python :: 3
Classifier: Programming Language :: Python :: 3.8
Classifier: Programming Language :: Python :: 3.9
Classifier: Programming Language :: Python :: 3.10
Classifier: Programming Language :: Python :: 3.11
Classifier: Programming Language :: Python :: 3 :: Only
Classifier: Topic :: Security
Classifier: Topic :: Software Development :: Libraries :: Python Modules
Classifier: Typing :: Typed
Requires-Dist: Flask (>=1.1,<2.0)
Requires-Dist: PyJWT (>=2.1.0,<3.0.0)
Requires-Dist: cryptography (>=3.4.7,<4.0.0)
Requires-Dist: markupsafe (==2.0.1)
Requires-Dist: python-dotenv (>=0.17.1,<0.18.0)
Project-URL: Repository, https://github.com/Septem151/Flask_PyJWT
